{"navVariant":"base","head":{"title":"Performance Management  | Moonstone Advocates","description":"Addressing under-performance can be tricky, leading to legal complexities. You need to keep things fair, protect your business, and follow employment law and ACAS guidance. If it’s not handled properly, you risk grievances, discrimination claims, or unfair dismissal cases. We can deliver clear, confident support at every stage of the performance management process.","ogTitle":"Performance Management  | Moonstone Advocates","ogDescription":"Addressing under-performance can be tricky, leading to legal complexities. You need to keep things fair, protect your business, and follow employment law and ACAS guidance. If it’s not handled properly, you risk grievances, discrimination claims, or unfair dismissal cases. We can deliver clear, confident support at every stage of the performance management process.","ogType":"website","twitterCard":"summary_large_image","canonical":"performance-management.html","jsonLd":["{\n  \"@context\": \"https://schema.org\",\n  \"@type\": \"WebPage\",\n  \"name\": \"Performance Management \",\n  \"description\": \"Addressing under-performance can be tricky, leading to legal complexities. You need to keep things fair, protect your business, and follow employment law and ACAS guidance. If it’s not handled properly, you risk grievances, discrimination claims, or unfair dismissal cases. We can deliver clear, confident support at every stage of the performance management process.\",\n  \"url\": \"/for-businesses/employment-hr/performance-management\",\n  \"inLanguage\": \"en\",\n  \"isPartOf\": {\n    \"@type\": \"WebSite\",\n    \"name\": \"Moonstone Advocates\",\n    \"url\": \"https://www.moonstone.co.ug\"\n  },\n  \"about\": {\n    \"@type\": \"Service\",\n    \"name\": \"Performance Management \",\n    \"description\": \"Addressing under-performance can be tricky, leading to legal complexities. You need to keep things fair, protect your business, and follow employment law and ACAS guidance. If it’s not handled properly, you risk grievances, discrimination claims, or unfair dismissal cases. We can deliver clear, confident support at every stage of the performance management process.\",\n    \"provider\": {\n      \"@type\": \"LegalService\",\n      \"name\": \"Moonstone Advocates\",\n      \"url\": \"https://www.moonstone.co.ug\"\n    },\n    \"serviceType\": \"Employment & HR Legal Services\",\n    \"areaServed\": \"UG\"\n  },\n  \"breadcrumb\": {\n    \"@type\": \"BreadcrumbList\",\n    \"itemListElement\": [\n      {\n        \"@type\": \"ListItem\",\n        \"position\": 1,\n        \"name\": \"Home\",\n        \"item\": \"/\"\n      },\n      {\n        \"@type\": \"ListItem\",\n        \"position\": 2,\n        \"name\": \"For businesses\",\n        \"item\": \"/for-businesses\"\n      },\n      {\n        \"@type\": \"ListItem\",\n        \"position\": 3,\n        \"name\": \"Employment & HR\",\n        \"item\": \"/for-businesses/employment-hr\"\n      },\n      {\n        \"@type\": \"ListItem\",\n        \"position\": 4,\n        \"name\": \"Performance Management \"\n      }\n    ]\n  },\n  \"mainEntity\": {\n    \"@type\": \"FAQPage\",\n    \"mainEntity\": [\n      {\n        \"@type\": \"Question\",\n        \"name\": \"What is performance management?\",\n        \"acceptedAnswer\": {\n          \"@type\": \"Answer\",\n          \"text\": \"It’s a structured way to deal with under-performance and help employees improve, while staying compliant with employment law.\"\n        }\n      },\n      {\n        \"@type\": \"Question\",\n        \"name\": \"When should I start a PIP?\",\n        \"acceptedAnswer\": {\n          \"@type\": \"Answer\",\n          \"text\": \"When informal feedback hasn’t worked and there’s clear evidence of ongoing under-performance.\"\n        }\n      },\n      {\n        \"@type\": \"Question\",\n        \"name\": \"Do I need a written capability policy?\",\n        \"acceptedAnswer\": {\n          \"@type\": \"Answer\",\n          \"text\": \"Yes. A written policy sets expectations, keeps things consistent and makes your decisions fair and easier to defend.\"\n        }\n      },\n      {\n        \"@type\": \"Question\",\n        \"name\": \"What are reasonable adjustments?\",\n        \"acceptedAnswer\": {\n          \"@type\": \"Answer\",\n          \"text\": \"These are changes you make to help disabled employees carry out their role without disadvantage.\"\n        }\n      },\n      {\n        \"@type\": \"Question\",\n        \"name\": \"Can I dismiss someone for poor performance?\",\n        \"acceptedAnswer\": {\n          \"@type\": \"Answer\",\n          \"text\": \"Yes, but only after a fair process that includes support, clear warnings, and reasonable adjustments where relevant.\"\n        }\n      },\n      {\n        \"@type\": \"Question\",\n        \"name\": \"What is ACAS Early Conciliation?\",\n        \"acceptedAnswer\": {\n          \"@type\": \"Answer\",\n          \"text\": \"It’s a process where ACAS helps employers and employees try to settle disputes before they go to Tribunal.\"\n        }\n      }\n    ]\n  },\n  \"datePublished\": \"2026-07-10T14:54:39.770Z\",\n  \"dateModified\": \"2026-07-10T14:54:39.770Z\"\n}"]},"blocks":[{"tag":"main","attrs":{"className":"main-wrapper"},"html":"<header data-wf--02-standard-header--variant=\"dark\" data-wf-component-id=\"949280b8-8e72-c6a2-5bfc-7cfb2eeda9b8\" data-wf-variant-state=\"8c1228b1-e5f0-eb03-34af-789b7e070b17\" class=\"section_header w-variant-8c1228b1-e5f0-eb03-34af-789b7e070b17\"><div class=\"padding-global is-page-top\"><div class=\"container-large\"><div class=\"simple_header-component\"><div class=\"padding-section-large\"><div class=\"simple_header_grid\"><div id=\"w-node-_8b2fa05c-57cd-b490-ced6-6fac2cf8719e-2eeda9b8\" class=\"simple_header_grid-left\"><div class=\"margin-bottom margin-small\"><h1 class=\"heading-style-h1\">Performance Management </h1></div><p class=\"text-size-medium\">Addressing under-performance can be tricky, leading to legal complexities. You need to keep things fair, protect your business, and follow employment law and ACAS guidance. If it’s not handled properly, you risk grievances, discrimination claims, or unfair dismissal cases. We can deliver clear, confident support at every stage of the performance management process.</p><div class=\"margin-top margin-medium\"><div class=\"button-group\"><a arrow-rotate=\"trigger\" data-btn-hover=\"\" data-theme=\"primary\" href=\"/contact\" class=\"btn is-icon w-inline-block\"><div class=\"btn__bg\"></div><div class=\"btn__circle-wrap\"><div class=\"btn__circle\"><div class=\"before__100\"></div></div></div><div class=\"btn__text\"><p class=\"btn-text-p\">Speak to an expert</p></div><div btn-arrow=\"right\" class=\"arrow is-button\"><div class=\"icon-embed-xsmall w-embed\"><svg xmlns=\"http://www.w3.org/2000/svg\" xmlns:xlink=\"http://www.w3.org/1999/xlink\" aria-hidden=\"true\" role=\"img\" class=\"iconify iconify--ic\" width=\"100%\" height=\"100%\" preserveAspectRatio=\"xMidYMid meet\" viewBox=\"0 0 24 24\"><path fill=\"currentColor\" d=\"M5 13h11.17l-4.88 4.88c-.39.39-.39 1.03 0 1.42s1.02.39 1.41 0l6.59-6.59a.996.996 0 0 0 0-1.41l-6.58-6.6a.996.996 0 1 0-1.41 1.41L16.17 11H5c-.55 0-1 .45-1 1s.45 1 1 1\"></path></svg></div></div></a></div></div></div><div id=\"w-node-_8b2fa05c-57cd-b490-ced6-6fac2cf871aa-2eeda9b8\" class=\"simple_header_grid-right\"><div class=\"simple-header_image-wrapper\"><img loading=\"eager\" src=\"https://cdn.prod.website-files.com/68b448d2e0ae8eda7aa370e3/68b448d4e0ae8eda7aa37155_placeholder-image.svg\" alt=\"Grey image placeholder with image icon centralised\" class=\"simple-header_image\"></div></div></div></div></div></div><div class=\"divider-horizontal\"></div><div class=\"container-large\"><div class=\"simple_header-component\"><div class=\"padding-section-xsmall\"><div class=\"breadcrumb_component\"><div data-wf--breadcrumb-original--variant=\"base\" class=\"breadcrumb_component\"><div class=\"breadcrumb_div\"><a href=\"/\" class=\"breadcrumb_link w-inline-block\"><div class=\"breadcrumb_page\">Home</div></a><div class=\"breadcrumb_icon w-embed\"><svg xmlns=\"http://www.w3.org/2000/svg\" xmlns:xlink=\"http://www.w3.org/1999/xlink\" aria-hidden=\"true\" role=\"img\" class=\"iconify iconify--ic\" width=\"100%\" height=\"100%\" preserveAspectRatio=\"xMidYMid meet\" viewBox=\"0 0 24 24\"><path fill=\"currentColor\" d=\"M5 13h11.17l-4.88 4.88c-.39.39-.39 1.03 0 1.42s1.02.39 1.41 0l6.59-6.59a.996.996 0 0 0 0-1.41l-6.58-6.6a.996.996 0 1 0-1.41 1.41L16.17 11H5c-.55 0-1 .45-1 1s.45 1 1 1\"></path></svg></div></div><div class=\"breadcrumb_div\"><a href=\"/for-businesses\" class=\"breadcrumb_link w-inline-block\"><div class=\"breadcrumb_page\">For businesses</div></a><div class=\"breadcrumb_icon w-embed\"><svg xmlns=\"http://www.w3.org/2000/svg\" xmlns:xlink=\"http://www.w3.org/1999/xlink\" aria-hidden=\"true\" role=\"img\" class=\"iconify iconify--ic\" width=\"100%\" height=\"100%\" preserveAspectRatio=\"xMidYMid meet\" viewBox=\"0 0 24 24\"><path fill=\"currentColor\" d=\"M5 13h11.17l-4.88 4.88c-.39.39-.39 1.03 0 1.42s1.02.39 1.41 0l6.59-6.59a.996.996 0 0 0 0-1.41l-6.58-6.6a.996.996 0 1 0-1.41 1.41L16.17 11H5c-.55 0-1 .45-1 1s.45 1 1 1\"></path></svg></div></div><div class=\"breadcrumb_div\"><div class=\"breadcrumb_current-page\">Performance Management </div></div></div></div></div></div></div></div><div class=\"listing_shape-wrapper w-variant-8c1228b1-e5f0-eb03-34af-789b7e070b17\"><div lottie=\"target-load\" class=\"header_shape is-standard\" data-w-id=\"5d828c84-1f1c-1e38-bfb3-80ffb8d04940\" data-animation-type=\"lottie\" data-src=\"https://cdn.prod.website-files.com/68b448d2e0ae8eda7aa370e3/69db9824cf9ff19dd03c1c29_08fdbca2c62ae345f765f433c8401fe4_Blacks_V_Blue.json\" data-loop=\"0\" data-direction=\"1\" data-autoplay=\"1\" data-is-ix2-target=\"0\" data-renderer=\"svg\" data-default-duration=\"0\" data-duration=\"0\" data-loading=\"lazy\"></div></div><div class=\"simple-header_background-image-wrapper\"><div class=\"image-overlay-layer\"></div><img loading=\"eager\" src=\"https://cdn.prod.website-files.com/68b448d2e0ae8eda7aa370e3/68b448d4e0ae8eda7aa37155_placeholder-image.svg\" alt=\"Grey image placeholder with image icon centralised\" class=\"simple-header_background-image\"></div></header><section class=\"section_benefit-grid_layout\"><div class=\"padding-global\"><div class=\"container-large\"><div class=\"padding-section-large\"><div class=\"benefit-grid_component\"><div class=\"w-layout-grid benefit-grid_list\"><div class=\"benefit-grid_item\"><div class=\"w-richtext\"><h4>Tailored capability and performance policies</h4><p>We write and update practical, tailored policies that are practical, legally compliant and aligned with your operations.</p><p>‍</p></div></div><div class=\"benefit-grid_item\"><div class=\"w-richtext\"><h4>Setting objectives, appraisals and gathering evidence</h4><p>We’ll help you with measurable objectives, fair appraisal frameworks, and evidential records to support lawful capability decisions.</p><p>‍</p></div></div><div class=\"benefit-grid_item\"><div class=\"w-richtext\"><h4><strong>Managertraining and making adjustments</strong></h4><p>With effective manager training, we can help you conduct reviews professionally, provide constructive feedback, take accurate notes, and manage reasonable adjustments where needed.</p><p>‍</p></div></div><div class=\"benefit-grid_item\"><div class=\"w-richtext\"><h4>Supportive and structured performance improvement plans (PIPs)</h4><p>We create performance plans with clear expectations, timelines, support measures and milestones to help employees improve while protecting your business.</p><p>‍</p></div></div><div class=\"benefit-grid_item\"><div class=\"w-richtext\"><h4>Managing sickness, mental health and protected characteristics </h4><p>Guidance through cases involving sickness, mental health, pregnancy or other protected characteristics, helping you manage risk of discrimination and treating people fairly.</p><p>‍</p></div></div><div class=\"benefit-grid_item\"><div class=\"w-richtext\"><h4>Representation at ACAS and Tribunal</h4><p>If early resolution isn’t possible, we’ll represent you at ACAS Early Conciliation and defend your position at Tribunal if a claim is made.</p><p>‍</p></div></div><div class=\"benefit-grid_item w-condition-invisible\"><div class=\"w-dyn-bind-empty w-richtext\"></div></div><div class=\"benefit-grid_item w-condition-invisible\"><div class=\"w-dyn-bind-empty w-richtext\"></div></div><div class=\"benefit-grid_item w-condition-invisible\"><div class=\"w-dyn-bind-empty w-richtext\"></div></div></div></div></div></div></div></section><section class=\"section_accordion\"><div class=\"padding-global\"><div class=\"container-large\"><div class=\"padding-section-large\"><div class=\"faq6_component\"><div class=\"w-layout-grid faq6_content\"><div class=\"faq6_content-left\"><h2>Questions we’re often asked</h2><div class=\"margin-top margin-small\"><div class=\"button-group\"><a href=\"/contact\" class=\"button is-secondary w-button\">Speak to an expert</a></div></div></div><div class=\"faq6_list\"><div class=\"w-layout-grid faq6_list-grid\"><div class=\"faq6_accordion\"><div data-w-id=\"2d4f5f46-8657-6adf-b3b2-ede2787f7f7d\" class=\"faq6_question\"><div>What is performance management?</div><div class=\"faq6_icon-wrapper\"><div class=\"icon-embed-small w-embed\"><svg width=\"100%\" height=\"100%\" viewBox=\"0 0 32 32\" fill=\"none\" xmlns=\"http://www.w3.org/2000/svg\">\n<path d=\"M25.3333 15.667V16.3336C25.3333 16.7018 25.0349 17.0003 24.6667 17.0003H17V24.667C17 25.0351 16.7015 25.3336 16.3333 25.3336H15.6667C15.2985 25.3336 15 25.0351 15 24.667V17.0003H7.3333C6.96511 17.0003 6.66663 16.7018 6.66663 16.3336V15.667C6.66663 15.2988 6.96511 15.0003 7.3333 15.0003H15V7.33365C15 6.96546 15.2985 6.66699 15.6667 6.66699H16.3333C16.7015 6.66699 17 6.96546 17 7.33365V15.0003H24.6667C25.0349 15.0003 25.3333 15.2988 25.3333 15.667Z\" fill=\"currentColor\"></path>\n</svg></div></div></div><div class=\"faq6_answer\"><div class=\"margin-bottom margin-small\"><div class=\"max-width-large\"><p>It’s a structured way to deal with under-performance and help employees improve, while staying compliant with employment law.</p></div></div></div></div><div class=\"faq6_accordion\"><div data-w-id=\"2d4f5f46-8657-6adf-b3b2-ede2787f7f88\" class=\"faq6_question\"><div>When should I start a PIP?</div><div class=\"faq6_icon-wrapper\"><div class=\"icon-embed-small w-embed\"><svg width=\"100%\" height=\"100%\" viewBox=\"0 0 32 32\" fill=\"none\" xmlns=\"http://www.w3.org/2000/svg\">\n<path d=\"M25.3333 15.667V16.3336C25.3333 16.7018 25.0349 17.0003 24.6667 17.0003H17V24.667C17 25.0351 16.7015 25.3336 16.3333 25.3336H15.6667C15.2985 25.3336 15 25.0351 15 24.667V17.0003H7.3333C6.96511 17.0003 6.66663 16.7018 6.66663 16.3336V15.667C6.66663 15.2988 6.96511 15.0003 7.3333 15.0003H15V7.33365C15 6.96546 15.2985 6.66699 15.6667 6.66699H16.3333C16.7015 6.66699 17 6.96546 17 7.33365V15.0003H24.6667C25.0349 15.0003 25.3333 15.2988 25.3333 15.667Z\" fill=\"currentColor\"></path>\n</svg></div></div></div><div class=\"faq6_answer\"><div class=\"margin-bottom margin-small\"><div class=\"max-width-large\"><p>When informal feedback hasn’t worked and there’s clear evidence of ongoing under-performance.</p></div></div></div></div><div class=\"faq6_accordion\"><div data-w-id=\"2d4f5f46-8657-6adf-b3b2-ede2787f7f93\" class=\"faq6_question\"><div>Do I need a written capability policy?</div><div class=\"faq6_icon-wrapper\"><div class=\"icon-embed-small w-embed\"><svg width=\"100%\" height=\"100%\" viewBox=\"0 0 32 32\" fill=\"none\" xmlns=\"http://www.w3.org/2000/svg\">\n<path d=\"M25.3333 15.667V16.3336C25.3333 16.7018 25.0349 17.0003 24.6667 17.0003H17V24.667C17 25.0351 16.7015 25.3336 16.3333 25.3336H15.6667C15.2985 25.3336 15 25.0351 15 24.667V17.0003H7.3333C6.96511 17.0003 6.66663 16.7018 6.66663 16.3336V15.667C6.66663 15.2988 6.96511 15.0003 7.3333 15.0003H15V7.33365C15 6.96546 15.2985 6.66699 15.6667 6.66699H16.3333C16.7015 6.66699 17 6.96546 17 7.33365V15.0003H24.6667C25.0349 15.0003 25.3333 15.2988 25.3333 15.667Z\" fill=\"currentColor\"></path>\n</svg></div></div></div><div class=\"faq6_answer\"><div class=\"margin-bottom margin-small\"><div class=\"max-width-large\"><p>Yes. A written policy sets expectations, keeps things consistent and makes your decisions fair and easier to defend.</p></div></div></div></div><div class=\"faq6_accordion\"><div data-w-id=\"2d4f5f46-8657-6adf-b3b2-ede2787f7f9e\" class=\"faq6_question\"><div>What are reasonable adjustments?</div><div class=\"faq6_icon-wrapper\"><div class=\"icon-embed-small w-embed\"><svg width=\"100%\" height=\"100%\" viewBox=\"0 0 32 32\" fill=\"none\" xmlns=\"http://www.w3.org/2000/svg\">\n<path d=\"M25.3333 15.667V16.3336C25.3333 16.7018 25.0349 17.0003 24.6667 17.0003H17V24.667C17 25.0351 16.7015 25.3336 16.3333 25.3336H15.6667C15.2985 25.3336 15 25.0351 15 24.667V17.0003H7.3333C6.96511 17.0003 6.66663 16.7018 6.66663 16.3336V15.667C6.66663 15.2988 6.96511 15.0003 7.3333 15.0003H15V7.33365C15 6.96546 15.2985 6.66699 15.6667 6.66699H16.3333C16.7015 6.66699 17 6.96546 17 7.33365V15.0003H24.6667C25.0349 15.0003 25.3333 15.2988 25.3333 15.667Z\" fill=\"currentColor\"></path>\n</svg></div></div></div><div class=\"faq6_answer\"><div class=\"margin-bottom margin-small\"><div class=\"max-width-large\"><p>These are changes you make to help disabled employees carry out their role without disadvantage.</p></div></div></div></div><div class=\"faq6_accordion\"><div data-w-id=\"2d4f5f46-8657-6adf-b3b2-ede2787f7fa9\" class=\"faq6_question\"><div>Can I dismiss someone for poor performance?</div><div class=\"faq6_icon-wrapper\"><div class=\"icon-embed-small w-embed\"><svg width=\"100%\" height=\"100%\" viewBox=\"0 0 32 32\" fill=\"none\" xmlns=\"http://www.w3.org/2000/svg\">\n<path d=\"M25.3333 15.667V16.3336C25.3333 16.7018 25.0349 17.0003 24.6667 17.0003H17V24.667C17 25.0351 16.7015 25.3336 16.3333 25.3336H15.6667C15.2985 25.3336 15 25.0351 15 24.667V17.0003H7.3333C6.96511 17.0003 6.66663 16.7018 6.66663 16.3336V15.667C6.66663 15.2988 6.96511 15.0003 7.3333 15.0003H15V7.33365C15 6.96546 15.2985 6.66699 15.6667 6.66699H16.3333C16.7015 6.66699 17 6.96546 17 7.33365V15.0003H24.6667C25.0349 15.0003 25.3333 15.2988 25.3333 15.667Z\" fill=\"currentColor\"></path>\n</svg></div></div></div><div class=\"faq6_answer\"><div class=\"margin-bottom margin-small\"><div class=\"max-width-large\"><p>Yes, but only after a fair process that includes support, clear warnings, and reasonable adjustments where relevant.</p></div></div></div></div><div class=\"faq6_accordion\"><div data-w-id=\"0a8deace-1e08-c9a3-2888-1d317fe93eb6\" class=\"faq6_question\"><div>What is ACAS Early Conciliation?</div><div class=\"faq6_icon-wrapper\"><div class=\"icon-embed-small w-embed\"><svg width=\"100%\" height=\"100%\" viewBox=\"0 0 32 32\" fill=\"none\" xmlns=\"http://www.w3.org/2000/svg\">\n<path d=\"M25.3333 15.667V16.3336C25.3333 16.7018 25.0349 17.0003 24.6667 17.0003H17V24.667C17 25.0351 16.7015 25.3336 16.3333 25.3336H15.6667C15.2985 25.3336 15 25.0351 15 24.667V17.0003H7.3333C6.96511 17.0003 6.66663 16.7018 6.66663 16.3336V15.667C6.66663 15.2988 6.96511 15.0003 7.3333 15.0003H15V7.33365C15 6.96546 15.2985 6.66699 15.6667 6.66699H16.3333C16.7015 6.66699 17 6.96546 17 7.33365V15.0003H24.6667C25.0349 15.0003 25.3333 15.2988 25.3333 15.667Z\" fill=\"currentColor\"></path>\n</svg></div></div></div><div class=\"faq6_answer\"><div class=\"margin-bottom margin-small\"><div class=\"max-width-large\"><p>It’s a process where ACAS helps employers and employees try to settle disputes before they go to Tribunal.</p></div></div></div></div></div></div></div></div></div></div></div></section><div class=\"section_testimonial\"><div class=\"w-embed\"><style>\n.section_testimonial:has(.w-dyn-empty) {\n  display: none;\n}\n</style></div><div class=\"padding-section-large\"><div class=\"divider-horizontal\"></div><div class=\"padding-global\"><div class=\"container-large\"><div fs-slider-type=\"cms\" fs-slider-instance=\"fs-1-card-slider\" class=\"fs-1-card-slider_instance\"><div class=\"fs-1-card-slider_navigation-wrapper\"><div class=\"testimonial_icon-wrapper\"><img loading=\"lazy\" src=\"/assets/69010fb7542aa2ee07e42406_quote-2.svg\" alt=\"\" class=\"testimonial_icon\"></div><div fs-slider-element=\"navigation\" class=\"fs-1-card-slider_navigation\"><button fs-slider-element=\"previous\" class=\"fs-1-card-slider_button\"><div class=\"icon-embed-small w-embed\"><svg xmlns=\"http://www.w3.org/2000/svg\" xmlns:xlink=\"http://www.w3.org/1999/xlink\" aria-hidden=\"true\" role=\"img\" class=\"iconify iconify--ic\" width=\"100%\" height=\"100%\" preserveAspectRatio=\"xMidYMid meet\" viewBox=\"0 0 24 24\"><path fill=\"currentColor\" d=\"M14.71 15.88L10.83 12l3.88-3.88a.996.996 0 1 0-1.41-1.41L8.71 11.3a.996.996 0 0 0 0 1.41l4.59 4.59c.39.39 1.02.39 1.41 0c.38-.39.39-1.03 0-1.42\"></path></svg></div></button><button fs-slider-element=\"next\" class=\"fs-1-card-slider_button\"><div class=\"icon-embed-small w-embed\"><svg xmlns=\"http://www.w3.org/2000/svg\" xmlns:xlink=\"http://www.w3.org/1999/xlink\" aria-hidden=\"true\" role=\"img\" class=\"iconify iconify--ic\" width=\"100%\" height=\"100%\" preserveAspectRatio=\"xMidYMid meet\" viewBox=\"0 0 24 24\"><path fill=\"currentColor\" d=\"M9.29 15.88L13.17 12L9.29 8.12a.996.996 0 1 1 1.41-1.41l4.59 4.59c.39.39.39 1.02 0 1.41L10.7 17.3a.996.996 0 0 1-1.41 0c-.38-.39-.39-1.03 0-1.42\"></path></svg></div></button></div></div><div fs-slider-element=\"list-wrapper\" class=\"fs-1-card-slider_list-wrapper w-dyn-list\"><div fs-slider-element=\"list\" role=\"list\" class=\"fs-1-card-slider_list w-dyn-items\"><div fs-slider-element=\"slide\" role=\"listitem\" class=\"fs-1-card-slider_slide w-dyn-item\"><div class=\"heading-style-h6\">Trusted by organisations, families and professionals across Uganda</div><div class=\"heading-style-h4\">Georgia was incredibly helpful throughout the process of reaching a settlement with a previous employer. Georgia took the time to understand my personal situation and provided clear, considerate, and professional guidance at every stage. Her support made a complex process much easier to navigate, and I felt reassured knowing I was in capable hands.</div><div class=\"testimonial_attribute\"><div class=\"testimonial_personal-details\"><div class=\"text-weight-semibold\">Employment Client</div></div></div></div><div fs-slider-element=\"slide\" role=\"listitem\" class=\"fs-1-card-slider_slide w-dyn-item\"><div class=\"heading-style-h6\">Trusted by organisations, families and professionals across Uganda</div><div class=\"heading-style-h4\">Chris is a great listener, clear communicator and, in my opinion, a genuinely good, kind human being. I have no hesitation in recommending Moonstone in Kampala for any legal matters you may have; you&#x27;ll be in good hands.</div><div class=\"testimonial_attribute\"><div class=\"testimonial_personal-details\"><div class=\"text-weight-semibold\">Employment Client</div></div></div></div><div fs-slider-element=\"slide\" role=\"listitem\" class=\"fs-1-card-slider_slide w-dyn-item\"><div class=\"heading-style-h6\">Trusted by organisations, families and professionals across Uganda</div><div class=\"heading-style-h4\">I have dealt with Chris Allen recently concerning some rather upsetting and extremely delicate matters. Chris and the team have proved to be reassuring, down to earth and absolute consummate professionals.</div><div class=\"testimonial_attribute\"><div class=\"testimonial_personal-details\"><div class=\"text-weight-semibold\">Employment Client</div></div></div></div><div fs-slider-element=\"slide\" role=\"listitem\" class=\"fs-1-card-slider_slide w-dyn-item\"><div class=\"heading-style-h6\">Trusted by organisations, families and professionals across Uganda</div><div class=\"heading-style-h4\">Moonstone helped us think beyond the sessions by supporting us to consider how the legislative changes translate into day to day behaviours and what this means for our culture in anticipation for our policy to be launched. This has supported follow on training delivery internally surrounding misogyny, misogynoir and trans-misogyny. </div><div class=\"testimonial_attribute\"><div class=\"testimonial_personal-details\"><div class=\"text-weight-semibold\">Employment Training Client </div></div></div></div><div fs-slider-element=\"slide\" role=\"listitem\" class=\"fs-1-card-slider_slide w-dyn-item\"><div class=\"heading-style-h6\">Trusted by organisations, families and professionals across Uganda</div><div class=\"heading-style-h4\">We had an excellent experience working with Moonstone. From the moment we reached out to request training, they responded quickly and took the time to meet with us early on to understand our needs and the wider organisational context. They were patient and flexible as we worked through our planning.</div><div class=\"testimonial_attribute\"><div class=\"testimonial_personal-details\"><div class=\"text-weight-semibold\">Employment Training Client </div></div></div></div><div fs-slider-element=\"slide\" role=\"listitem\" class=\"fs-1-card-slider_slide w-dyn-item\"><div class=\"heading-style-h6\">Trusted by organisations, families and professionals across Uganda</div><div class=\"heading-style-h4\">Ellie was absolutely amazing through the whole process. She made me feel at ease and was very efficient at replying to my emails and queries. I would also like to say a thank you to Jemma who was the first one I engaged with and made me feel comfortable and less anxious.</div><div class=\"testimonial_attribute\"><div class=\"testimonial_personal-details\"><div class=\"text-weight-semibold\">Employment Client</div></div></div></div><div fs-slider-element=\"slide\" role=\"listitem\" class=\"fs-1-card-slider_slide w-dyn-item\"><div class=\"heading-style-h6\">Trusted by organisations, families and professionals across Uganda</div><div class=\"heading-style-h4\">I worked with Tom during a very stressful and time-sensitive settlement, and I’m genuinely so grateful for his support. From the start, he was calm, practical and incredibly thorough, which made a huge difference at a point when everything felt overwhelming.</div><div class=\"testimonial_attribute\"><div class=\"testimonial_personal-details\"><div class=\"text-weight-semibold\">Employment Client</div></div></div></div><div fs-slider-element=\"slide\" role=\"listitem\" class=\"fs-1-card-slider_slide w-dyn-item\"><div class=\"heading-style-h6\">Trusted by organisations, families and professionals across Uganda</div><div class=\"heading-style-h4\">The service was 11 out of 10! Ellie kept me on the straight and narrow. She navigated the legal side and the emotional side incredibly well. She advised me brilliantly and I couldn’t be happier with that</div><div class=\"testimonial_attribute\"><div class=\"testimonial_personal-details\"><div class=\"text-weight-semibold\">Employment Client </div></div></div></div><div fs-slider-element=\"slide\" role=\"listitem\" class=\"fs-1-card-slider_slide w-dyn-item\"><div class=\"heading-style-h6\">Trusted by organisations, families and professionals across Uganda</div><div class=\"heading-style-h4\">Euan Lawrence helped me with a HR issue with a former employee, and I was extremely impressed by his professionalism and the clarity of his advice in translating complex legal ease for the less legally minded individuals such as myself – I would fully recommend.</div><div class=\"testimonial_attribute\"><div class=\"testimonial_personal-details\"><div class=\"text-weight-semibold\">Employment Client</div></div></div></div><div fs-slider-element=\"slide\" role=\"listitem\" class=\"fs-1-card-slider_slide w-dyn-item\"><div class=\"heading-style-h6\">Trusted by organisations, families and professionals across Uganda</div><div class=\"heading-style-h4\">Outstanding service from start to finish. The team’s work rate, speed of response, and legal knowledge were second to none. They consistently went above and\nbeyond to get things done efficiently and with care. Special thanks to Richard P and Pete K for their exceptional support – true professionals!</div><div class=\"testimonial_attribute\"><div class=\"testimonial_personal-details\"><div class=\"text-weight-semibold\">Moonstone Client</div></div></div></div></div></div></div></div></div></div></div><div element-reveal=\"trigger\" class=\"section_team\"><div class=\"padding-global\"><div class=\"container-large\"><div class=\"padding-section-large\"><div class=\"slider-main_component\"><div fs-slider-type=\"cms\" fs-slider-instance=\"fs-4-card-slider\" class=\"fs-4-card-slider_instance\"><h2 data-scroll-speed=\"0.025\" data-scroll=\"\" class=\"heading-style-h2\">Experts in every area</h2><div fs-slider-element=\"list-wrapper\" class=\"fs-4-card-slider_list-wrapper w-dyn-list\"><div fs-slider-element=\"list\" role=\"list\" class=\"fs-4-card-slider_list w-dyn-items\"><div fs-slider-element=\"slide\" role=\"listitem\" class=\"fs-4-card-slider_slide w-dyn-item\"><div hover-zoom=\"trigger\" class=\"team-member_item\"><a href=\"/our-people/edward-labeja\" class=\"team-member_item w-inline-block\"><div class=\"margin-bottom margin-small\"><div class=\"team-member_image-wrapper\"><img hover-zoom=\"target\" loading=\"lazy\" alt=\"\" src=\"/assets/team/placeholder.svg\" class=\"image is-team\"></div></div><div class=\"team-member_text-wrapper\"><div fs-list-field=\"full-name\" class=\"text-size-large text-weight-semibold\">Edward Labeja</div><div class=\"hidden-text\"><div fs-list-field=\"first-name\">Edward</div><div fs-list-field=\"last-name\" class=\"text-size-large text-weight-semibold\">Labeja</div></div><div class=\"article-meta\"><div fs-list-field=\"job-title\" class=\"secondary_tag\">Partner</div></div></div></a></div></div><div fs-slider-element=\"slide\" role=\"listitem\" class=\"fs-4-card-slider_slide w-dyn-item\"><div hover-zoom=\"trigger\" class=\"team-member_item\"><a href=\"/our-people/edwin-michael-echiba\" class=\"team-member_item w-inline-block\"><div class=\"margin-bottom margin-small\"><div class=\"team-member_image-wrapper\"><img hover-zoom=\"target\" loading=\"lazy\" alt=\"\" src=\"/assets/team/placeholder.svg\" class=\"image is-team\"></div></div><div class=\"team-member_text-wrapper\"><div fs-list-field=\"full-name\" class=\"text-size-large text-weight-semibold\">Edwin Michael Echiba</div><div class=\"hidden-text\"><div fs-list-field=\"first-name\">Edwin</div><div fs-list-field=\"last-name\" class=\"text-size-large text-weight-semibold\">Michael Echiba</div></div><div class=\"article-meta\"><div fs-list-field=\"job-title\" class=\"secondary_tag\">Partner</div></div></div></a></div></div><div fs-slider-element=\"slide\" role=\"listitem\" class=\"fs-4-card-slider_slide w-dyn-item\"><div hover-zoom=\"trigger\" class=\"team-member_item\"><a href=\"/our-people/jonathan-tumushime\" class=\"team-member_item w-inline-block\"><div class=\"margin-bottom margin-small\"><div class=\"team-member_image-wrapper\"><img hover-zoom=\"target\" loading=\"lazy\" alt=\"\" src=\"/assets/team/placeholder.svg\" class=\"image is-team\"></div></div><div class=\"team-member_text-wrapper\"><div fs-list-field=\"full-name\" class=\"text-size-large text-weight-semibold\">Jonathan Tumushime</div><div class=\"hidden-text\"><div fs-list-field=\"first-name\">Jonathan</div><div fs-list-field=\"last-name\" class=\"text-size-large text-weight-semibold\">Tumushime</div></div><div class=\"article-meta\"><div fs-list-field=\"job-title\" class=\"secondary_tag\">Consultant</div></div></div></a></div></div><div fs-slider-element=\"slide\" role=\"listitem\" class=\"fs-4-card-slider_slide w-dyn-item\"><div hover-zoom=\"trigger\" class=\"team-member_item\"><a href=\"/our-people/norah-amanya\" class=\"team-member_item w-inline-block\"><div class=\"margin-bottom margin-small\"><div class=\"team-member_image-wrapper\"><img hover-zoom=\"target\" loading=\"lazy\" alt=\"\" src=\"/assets/team/placeholder.svg\" class=\"image is-team\"></div></div><div class=\"team-member_text-wrapper\"><div fs-list-field=\"full-name\" class=\"text-size-large text-weight-semibold\">Norah Amanya</div><div class=\"hidden-text\"><div fs-list-field=\"first-name\">Norah</div><div fs-list-field=\"last-name\" class=\"text-size-large text-weight-semibold\">Amanya</div></div><div class=\"article-meta\"><div fs-list-field=\"job-title\" class=\"secondary_tag\">Partner</div></div></div></a></div></div></div></div><div class=\"fs-4-card-slider_navigation-wrapper\"><div fs-slider-element=\"navigation\" class=\"fs-4-card-slider_navigation\"><button fs-slider-element=\"previous\" class=\"fs-4-card-slider_button\"><div class=\"icon-embed-small w-embed\"><svg xmlns=\"http://www.w3.org/2000/svg\" xmlns:xlink=\"http://www.w3.org/1999/xlink\" aria-hidden=\"true\" role=\"img\" class=\"iconify iconify--ic\" width=\"100%\" height=\"100%\" preserveAspectRatio=\"xMidYMid meet\" viewBox=\"0 0 24 24\"><path fill=\"currentColor\" d=\"M14.71 15.88L10.83 12l3.88-3.88a.996.996 0 1 0-1.41-1.41L8.71 11.3a.996.996 0 0 0 0 1.41l4.59 4.59c.39.39 1.02.39 1.41 0c.38-.39.39-1.03 0-1.42\"></path></svg></div></button><button fs-slider-element=\"next\" class=\"fs-4-card-slider_button\"><div class=\"icon-embed-small w-embed\"><svg xmlns=\"http://www.w3.org/2000/svg\" xmlns:xlink=\"http://www.w3.org/1999/xlink\" aria-hidden=\"true\" role=\"img\" class=\"iconify iconify--ic\" width=\"100%\" height=\"100%\" preserveAspectRatio=\"xMidYMid meet\" viewBox=\"0 0 24 24\"><path fill=\"currentColor\" d=\"M9.29 15.88L13.17 12L9.29 8.12a.996.996 0 1 1 1.41-1.41l4.59 4.59c.39.39.39 1.02 0 1.41L10.7 17.3a.996.996 0 0 1-1.41 0c-.38-.39-.39-1.03 0-1.42\"></path></svg></div></button></div></div></div></div></div></div></div></div><section class=\"section_cta17\"><div class=\"padding-global\"><div class=\"padding-section-large\"><div class=\"wrapper_wide-screen padding-0\"><div class=\"cta17_component\"><div class=\"w-layout-grid cta17_content\"><div class=\"cta17_content-left\"><div class=\"margin-bottom margin-small\"><div data-scroll-speed=\"0.025\" data-scroll=\"\" class=\"dynamic-heading_component\"><h2 class=\"heading-style-h2 is-cta-heading\">Need an expert in</h2><h2 class=\"heading-style-h2 is-cta-heading is-middle\">employment &amp; HR</h2><h2 class=\"heading-style-h2 is-cta-heading\">?</h2></div></div><div class=\"margin-bottom margin-medium\"><p class=\"text-size-medium\">For more information or a no obligation discussion, please call or email our team today.</p></div><div class=\"button-group\"><a arrow-rotate=\"trigger\" data-btn-hover=\"\" data-theme=\"primary\" href=\"tel:+441132070000\" class=\"btn is-icon w-inline-block\"><div class=\"btn__bg\"></div><div class=\"btn__circle-wrap\"><div class=\"btn__circle\"><div class=\"before__100\"></div></div></div><div class=\"btn__text\"><p class=\"btn-text-p\">Call us today</p></div><div btn-arrow=\"right\" class=\"arrow is-button\"><div class=\"icon-embed-xsmall w-embed\"><svg xmlns=\"http://www.w3.org/2000/svg\" xmlns:xlink=\"http://www.w3.org/1999/xlink\" aria-hidden=\"true\" role=\"img\" class=\"iconify iconify--ic\" width=\"100%\" height=\"100%\" preserveAspectRatio=\"xMidYMid meet\" viewBox=\"0 0 24 24\"><path fill=\"currentColor\" d=\"M5 13h11.17l-4.88 4.88c-.39.39-.39 1.03 0 1.42s1.02.39 1.41 0l6.59-6.59a.996.996 0 0 0 0-1.41l-6.58-6.6a.996.996 0 1 0-1.41 1.41L16.17 11H5c-.55 0-1 .45-1 1s.45 1 1 1\"></path></svg></div></div></a><a data-theme=\"light\" data-btn-hover=\"\" href=\"mailto:employmentenquiry@moonstone.co.ug\" class=\"btn w-inline-block\"><div class=\"btn__bg light\"></div><div class=\"btn__circle-wrap\"><div class=\"btn__circle light\"><div class=\"before__100\"></div></div></div><div class=\"btn__text light\"><p class=\"btn-text-p\">Email this team</p></div></a></div></div><div id=\"w-node-_0e283a4d-a2ed-14f8-c1cf-0bbfdc1c79b8-dc1c79af\" class=\"cta17_content-right\"><div class=\"div-block-19\"><img src=\"https://cdn.prod.website-files.com/68b448d2e0ae8eda7aa370e3/693701e372e346d3d962f387_Commercial%203%20(1)-min.avif\" loading=\"lazy\" sizes=\"(max-width: 479px) 48vw, (max-width: 991px) 49vw, (max-width: 4000px) 50vw, 2000px\" srcset=\"https://cdn.prod.website-files.com/68b448d2e0ae8eda7aa370e3/693701e372e346d3d962f387_Commercial%203%20(1)-min-p-500.avif 500w, https://cdn.prod.website-files.com/68b448d2e0ae8eda7aa370e3/693701e372e346d3d962f387_Commercial%203%20(1)-min-p-800.avif 800w, https://cdn.prod.website-files.com/68b448d2e0ae8eda7aa370e3/693701e372e346d3d962f387_Commercial%203%20(1)-min.avif 2000w\" alt=\"Smiling woman in a yellow shirt shaking hands with another person during a meeting.\" class=\"cta-cut-image\"><div shape-grow=\"\" data-scroll=\"\" data-scroll-speed=\"-0.05\" class=\"cta_image-shape\"><div class=\"shape_circle blue\"></div><div class=\"shape_line\"></div></div><img src=\"https://cdn.prod.website-files.com/68b448d2e0ae8eda7aa370e3/68fa18da520b64d54e3ea959_96688c06520a6a8dac4c077e7791ab4d_Commercial%203-min.jpg\" loading=\"lazy\" sizes=\"(max-width: 479px) 48vw, (max-width: 991px) 49vw, 50vw\" srcset=\"https://cdn.prod.website-files.com/68b448d2e0ae8eda7aa370e3/68fa18da520b64d54e3ea959_96688c06520a6a8dac4c077e7791ab4d_Commercial%203-min-p-500.jpg 500w, https://cdn.prod.website-files.com/68b448d2e0ae8eda7aa370e3/68fa18da520b64d54e3ea959_96688c06520a6a8dac4c077e7791ab4d_Commercial%203-min-p-800.jpg 800w, https://cdn.prod.website-files.com/68b448d2e0ae8eda7aa370e3/68fa18da520b64d54e3ea959_96688c06520a6a8dac4c077e7791ab4d_Commercial%203-min-p-1080.jpg 1080w, https://cdn.prod.website-files.com/68b448d2e0ae8eda7aa370e3/68fa18da520b64d54e3ea959_96688c06520a6a8dac4c077e7791ab4d_Commercial%203-min-p-1600.jpg 1600w, https://cdn.prod.website-files.com/68b448d2e0ae8eda7aa370e3/68fa18da520b64d54e3ea959_96688c06520a6a8dac4c077e7791ab4d_Commercial%203-min-p-2000.jpg 2000w, https://cdn.prod.website-files.com/68b448d2e0ae8eda7aa370e3/68fa18da520b64d54e3ea959_96688c06520a6a8dac4c077e7791ab4d_Commercial%203-min-p-2600.jpg 2600w, https://cdn.prod.website-files.com/68b448d2e0ae8eda7aa370e3/68fa18da520b64d54e3ea959_96688c06520a6a8dac4c077e7791ab4d_Commercial%203-min-p-3200.jpg 3200w, https://cdn.prod.website-files.com/68b448d2e0ae8eda7aa370e3/68fa18da520b64d54e3ea959_96688c06520a6a8dac4c077e7791ab4d_Commercial%203-min.jpg 5903w\" alt=\"Smiling woman in yellow shirt shaking hands with another person across a table in an office setting.\" class=\"image is-parallax\"></div></div></div></div></div></div></div></section><section class=\"section_crosslink\"><div class=\"padding-global\"><div class=\"container-large\"><div class=\"padding-section-large\"><div class=\"crosslink_component\"><div class=\"w-layout-grid crosslink_content\"><div class=\"crosslink_content-left\"><h2 class=\"heading-style-h3\">Other related services</h2></div><div class=\"crosslink_wrapper w-dyn-list\"><div role=\"list\" class=\"crosslink_item-list w-dyn-items\"><div role=\"listitem\" class=\"crosslink_item w-dyn-item\"><a list-link=\"trigger\" href=\"/working-time-regulations\" class=\"button is-text-link w-inline-block\"><div class=\"crosslink_item-text-wrapper\"><p>Working Time Regulations</p></div><div list-link=\"target\" class=\"crosslink_item-icon-wrapper\"><div class=\"icon-embed-xxsmall w-embed\"><svg xmlns=\"http://www.w3.org/2000/svg\" width=\"100%\" height=\"100%\" viewBox=\"0 -960 960 960\"><path fill=\"currentColor\" d=\"M676.2-445.93H188.09q-14.68 0-24.37-9.7-9.7-9.7-9.7-24.37 0-14.67 9.7-24.37 9.69-9.7 24.37-9.7H676.2L456.13-734.13q-10.2-10.2-10.33-24.03-.14-13.84 10.07-24.09 10.22-10.29 24.09-10.17 13.87.12 24.15 10.31l278 278q5.46 5.52 7.94 11.48 2.49 5.97 2.49 12.66t-2.49 12.63q-2.48 5.95-7.94 11.45l-278.24 278q-10.55 10.43-24.17 10.43-13.61 0-23.81-10.49-10.19-10.21-10.19-23.85 0-13.63 10.19-23.83l220.31-220.3Z\"></path></svg></div></div></a></div><div role=\"listitem\" class=\"crosslink_item w-dyn-item\"><a list-link=\"trigger\" href=\"/whistleblowing\" class=\"button is-text-link w-inline-block\"><div class=\"crosslink_item-text-wrapper\"><p>Whistleblowing</p></div><div list-link=\"target\" class=\"crosslink_item-icon-wrapper\"><div class=\"icon-embed-xxsmall w-embed\"><svg xmlns=\"http://www.w3.org/2000/svg\" width=\"100%\" height=\"100%\" viewBox=\"0 -960 960 960\"><path fill=\"currentColor\" d=\"M676.2-445.93H188.09q-14.68 0-24.37-9.7-9.7-9.7-9.7-24.37 0-14.67 9.7-24.37 9.69-9.7 24.37-9.7H676.2L456.13-734.13q-10.2-10.2-10.33-24.03-.14-13.84 10.07-24.09 10.22-10.29 24.09-10.17 13.87.12 24.15 10.31l278 278q5.46 5.52 7.94 11.48 2.49 5.97 2.49 12.66t-2.49 12.63q-2.48 5.95-7.94 11.45l-278.24 278q-10.55 10.43-24.17 10.43-13.61 0-23.81-10.49-10.19-10.21-10.19-23.85 0-13.63 10.19-23.83l220.31-220.3Z\"></path></svg></div></div></a></div><div role=\"listitem\" class=\"crosslink_item w-dyn-item\"><a list-link=\"trigger\" href=\"/unfair-and-wrongful-dismissal\" class=\"button is-text-link w-inline-block\"><div class=\"crosslink_item-text-wrapper\"><p>Unfair and Wrongful Dismissal </p></div><div list-link=\"target\" class=\"crosslink_item-icon-wrapper\"><div class=\"icon-embed-xxsmall w-embed\"><svg xmlns=\"http://www.w3.org/2000/svg\" width=\"100%\" height=\"100%\" viewBox=\"0 -960 960 960\"><path fill=\"currentColor\" d=\"M676.2-445.93H188.09q-14.68 0-24.37-9.7-9.7-9.7-9.7-24.37 0-14.67 9.7-24.37 9.69-9.7 24.37-9.7H676.2L456.13-734.13q-10.2-10.2-10.33-24.03-.14-13.84 10.07-24.09 10.22-10.29 24.09-10.17 13.87.12 24.15 10.31l278 278q5.46 5.52 7.94 11.48 2.49 5.97 2.49 12.66t-2.49 12.63q-2.48 5.95-7.94 11.45l-278.24 278q-10.55 10.43-24.17 10.43-13.61 0-23.81-10.49-10.19-10.21-10.19-23.85 0-13.63 10.19-23.83l220.31-220.3Z\"></path></svg></div></div></a></div><div role=\"listitem\" class=\"crosslink_item w-dyn-item\"><a list-link=\"trigger\" href=\"/transfer-of-undertakings-tupe\" class=\"button is-text-link w-inline-block\"><div class=\"crosslink_item-text-wrapper\"><p>Transfer of Undertakings (TUPE)</p></div><div list-link=\"target\" class=\"crosslink_item-icon-wrapper\"><div class=\"icon-embed-xxsmall w-embed\"><svg xmlns=\"http://www.w3.org/2000/svg\" width=\"100%\" height=\"100%\" viewBox=\"0 -960 960 960\"><path fill=\"currentColor\" d=\"M676.2-445.93H188.09q-14.68 0-24.37-9.7-9.7-9.7-9.7-24.37 0-14.67 9.7-24.37 9.69-9.7 24.37-9.7H676.2L456.13-734.13q-10.2-10.2-10.33-24.03-.14-13.84 10.07-24.09 10.22-10.29 24.09-10.17 13.87.12 24.15 10.31l278 278q5.46 5.52 7.94 11.48 2.49 5.97 2.49 12.66t-2.49 12.63q-2.48 5.95-7.94 11.45l-278.24 278q-10.55 10.43-24.17 10.43-13.61 0-23.81-10.49-10.19-10.21-10.19-23.85 0-13.63 10.19-23.83l220.31-220.3Z\"></path></svg></div></div></a></div><div role=\"listitem\" class=\"crosslink_item w-dyn-item\"><a list-link=\"trigger\" href=\"/tribunal-representation\" class=\"button is-text-link w-inline-block\"><div class=\"crosslink_item-text-wrapper\"><p>Tribunal Representation</p></div><div list-link=\"target\" class=\"crosslink_item-icon-wrapper\"><div class=\"icon-embed-xxsmall w-embed\"><svg xmlns=\"http://www.w3.org/2000/svg\" width=\"100%\" height=\"100%\" viewBox=\"0 -960 960 960\"><path fill=\"currentColor\" d=\"M676.2-445.93H188.09q-14.68 0-24.37-9.7-9.7-9.7-9.7-24.37 0-14.67 9.7-24.37 9.69-9.7 24.37-9.7H676.2L456.13-734.13q-10.2-10.2-10.33-24.03-.14-13.84 10.07-24.09 10.22-10.29 24.09-10.17 13.87.12 24.15 10.31l278 278q5.46 5.52 7.94 11.48 2.49 5.97 2.49 12.66t-2.49 12.63q-2.48 5.95-7.94 11.45l-278.24 278q-10.55 10.43-24.17 10.43-13.61 0-23.81-10.49-10.19-10.21-10.19-23.85 0-13.63 10.19-23.83l220.31-220.3Z\"></path></svg></div></div></a></div><div role=\"listitem\" class=\"crosslink_item w-dyn-item\"><a list-link=\"trigger\" href=\"/settlement-agreements-and-protected-conversations\" class=\"button is-text-link w-inline-block\"><div class=\"crosslink_item-text-wrapper\"><p>Settlement Agreements and Protected Conversations</p></div><div list-link=\"target\" class=\"crosslink_item-icon-wrapper\"><div class=\"icon-embed-xxsmall w-embed\"><svg xmlns=\"http://www.w3.org/2000/svg\" width=\"100%\" height=\"100%\" viewBox=\"0 -960 960 960\"><path fill=\"currentColor\" d=\"M676.2-445.93H188.09q-14.68 0-24.37-9.7-9.7-9.7-9.7-24.37 0-14.67 9.7-24.37 9.69-9.7 24.37-9.7H676.2L456.13-734.13q-10.2-10.2-10.33-24.03-.14-13.84 10.07-24.09 10.22-10.29 24.09-10.17 13.87.12 24.15 10.31l278 278q5.46 5.52 7.94 11.48 2.49 5.97 2.49 12.66t-2.49 12.63q-2.48 5.95-7.94 11.45l-278.24 278q-10.55 10.43-24.17 10.43-13.61 0-23.81-10.49-10.19-10.21-10.19-23.85 0-13.63 10.19-23.83l220.31-220.3Z\"></path></svg></div></div></a></div><div role=\"listitem\" class=\"crosslink_item w-dyn-item\"><a list-link=\"trigger\" href=\"/restrictive-covenants\" class=\"button is-text-link w-inline-block\"><div class=\"crosslink_item-text-wrapper\"><p>Restrictive Covenants </p></div><div list-link=\"target\" class=\"crosslink_item-icon-wrapper\"><div class=\"icon-embed-xxsmall w-embed\"><svg xmlns=\"http://www.w3.org/2000/svg\" width=\"100%\" height=\"100%\" viewBox=\"0 -960 960 960\"><path fill=\"currentColor\" d=\"M676.2-445.93H188.09q-14.68 0-24.37-9.7-9.7-9.7-9.7-24.37 0-14.67 9.7-24.37 9.69-9.7 24.37-9.7H676.2L456.13-734.13q-10.2-10.2-10.33-24.03-.14-13.84 10.07-24.09 10.22-10.29 24.09-10.17 13.87.12 24.15 10.31l278 278q5.46 5.52 7.94 11.48 2.49 5.97 2.49 12.66t-2.49 12.63q-2.48 5.95-7.94 11.45l-278.24 278q-10.55 10.43-24.17 10.43-13.61 0-23.81-10.49-10.19-10.21-10.19-23.85 0-13.63 10.19-23.83l220.31-220.3Z\"></path></svg></div></div></a></div><div role=\"listitem\" class=\"crosslink_item w-dyn-item\"><a list-link=\"trigger\" href=\"/restructuring\" class=\"button is-text-link w-inline-block\"><div class=\"crosslink_item-text-wrapper\"><p>Restructuring </p></div><div list-link=\"target\" class=\"crosslink_item-icon-wrapper\"><div class=\"icon-embed-xxsmall w-embed\"><svg xmlns=\"http://www.w3.org/2000/svg\" width=\"100%\" height=\"100%\" viewBox=\"0 -960 960 960\"><path fill=\"currentColor\" d=\"M676.2-445.93H188.09q-14.68 0-24.37-9.7-9.7-9.7-9.7-24.37 0-14.67 9.7-24.37 9.69-9.7 24.37-9.7H676.2L456.13-734.13q-10.2-10.2-10.33-24.03-.14-13.84 10.07-24.09 10.22-10.29 24.09-10.17 13.87.12 24.15 10.31l278 278q5.46 5.52 7.94 11.48 2.49 5.97 2.49 12.66t-2.49 12.63q-2.48 5.95-7.94 11.45l-278.24 278q-10.55 10.43-24.17 10.43-13.61 0-23.81-10.49-10.19-10.21-10.19-23.85 0-13.63 10.19-23.83l220.31-220.3Z\"></path></svg></div></div></a></div><div role=\"listitem\" class=\"crosslink_item w-dyn-item\"><a list-link=\"trigger\" href=\"/redundancy\" class=\"button is-text-link w-inline-block\"><div class=\"crosslink_item-text-wrapper\"><p>Redundancy </p></div><div list-link=\"target\" class=\"crosslink_item-icon-wrapper\"><div class=\"icon-embed-xxsmall w-embed\"><svg xmlns=\"http://www.w3.org/2000/svg\" width=\"100%\" height=\"100%\" viewBox=\"0 -960 960 960\"><path fill=\"currentColor\" d=\"M676.2-445.93H188.09q-14.68 0-24.37-9.7-9.7-9.7-9.7-24.37 0-14.67 9.7-24.37 9.69-9.7 24.37-9.7H676.2L456.13-734.13q-10.2-10.2-10.33-24.03-.14-13.84 10.07-24.09 10.22-10.29 24.09-10.17 13.87.12 24.15 10.31l278 278q5.46 5.52 7.94 11.48 2.49 5.97 2.49 12.66t-2.49 12.63q-2.48 5.95-7.94 11.45l-278.24 278q-10.55 10.43-24.17 10.43-13.61 0-23.81-10.49-10.19-10.21-10.19-23.85 0-13.63 10.19-23.83l220.31-220.3Z\"></path></svg></div></div></a></div><div role=\"listitem\" class=\"crosslink_item w-dyn-item\"><a list-link=\"trigger\" href=\"/recruitment\" class=\"button is-text-link w-inline-block\"><div class=\"crosslink_item-text-wrapper\"><p>Recruitment </p></div><div list-link=\"target\" class=\"crosslink_item-icon-wrapper\"><div class=\"icon-embed-xxsmall w-embed\"><svg xmlns=\"http://www.w3.org/2000/svg\" width=\"100%\" height=\"100%\" viewBox=\"0 -960 960 960\"><path fill=\"currentColor\" d=\"M676.2-445.93H188.09q-14.68 0-24.37-9.7-9.7-9.7-9.7-24.37 0-14.67 9.7-24.37 9.69-9.7 24.37-9.7H676.2L456.13-734.13q-10.2-10.2-10.33-24.03-.14-13.84 10.07-24.09 10.22-10.29 24.09-10.17 13.87.12 24.15 10.31l278 278q5.46 5.52 7.94 11.48 2.49 5.97 2.49 12.66t-2.49 12.63q-2.48 5.95-7.94 11.45l-278.24 278q-10.55 10.43-24.17 10.43-13.61 0-23.81-10.49-10.19-10.21-10.19-23.85 0-13.63 10.19-23.83l220.31-220.3Z\"></path></svg></div></div></a></div><div role=\"listitem\" class=\"crosslink_item w-dyn-item\"><a list-link=\"trigger\" href=\"/employment-policies-and-staff-handbooks\" class=\"button is-text-link w-inline-block\"><div class=\"crosslink_item-text-wrapper\"><p>Employment Policies and Staff Handbooks</p></div><div list-link=\"target\" class=\"crosslink_item-icon-wrapper\"><div class=\"icon-embed-xxsmall w-embed\"><svg xmlns=\"http://www.w3.org/2000/svg\" width=\"100%\" height=\"100%\" viewBox=\"0 -960 960 960\"><path fill=\"currentColor\" d=\"M676.2-445.93H188.09q-14.68 0-24.37-9.7-9.7-9.7-9.7-24.37 0-14.67 9.7-24.37 9.69-9.7 24.37-9.7H676.2L456.13-734.13q-10.2-10.2-10.33-24.03-.14-13.84 10.07-24.09 10.22-10.29 24.09-10.17 13.87.12 24.15 10.31l278 278q5.46 5.52 7.94 11.48 2.49 5.97 2.49 12.66t-2.49 12.63q-2.48 5.95-7.94 11.45l-278.24 278q-10.55 10.43-24.17 10.43-13.61 0-23.81-10.49-10.19-10.21-10.19-23.85 0-13.63 10.19-23.83l220.31-220.3Z\"></path></svg></div></div></a></div><div role=\"listitem\" class=\"crosslink_item w-dyn-item\"><a list-link=\"trigger\" href=\"/managing-sickness-absence\" class=\"button is-text-link w-inline-block\"><div class=\"crosslink_item-text-wrapper\"><p>Managing Sickness Absence </p></div><div list-link=\"target\" class=\"crosslink_item-icon-wrapper\"><div class=\"icon-embed-xxsmall w-embed\"><svg xmlns=\"http://www.w3.org/2000/svg\" width=\"100%\" height=\"100%\" viewBox=\"0 -960 960 960\"><path fill=\"currentColor\" d=\"M676.2-445.93H188.09q-14.68 0-24.37-9.7-9.7-9.7-9.7-24.37 0-14.67 9.7-24.37 9.69-9.7 24.37-9.7H676.2L456.13-734.13q-10.2-10.2-10.33-24.03-.14-13.84 10.07-24.09 10.22-10.29 24.09-10.17 13.87.12 24.15 10.31l278 278q5.46 5.52 7.94 11.48 2.49 5.97 2.49 12.66t-2.49 12.63q-2.48 5.95-7.94 11.45l-278.24 278q-10.55 10.43-24.17 10.43-13.61 0-23.81-10.49-10.19-10.21-10.19-23.85 0-13.63 10.19-23.83l220.31-220.3Z\"></path></svg></div></div></a></div><div role=\"listitem\" class=\"crosslink_item w-dyn-item\"><a list-link=\"trigger\" href=\"/ir35\" class=\"button is-text-link w-inline-block\"><div class=\"crosslink_item-text-wrapper\"><p>IR35</p></div><div list-link=\"target\" class=\"crosslink_item-icon-wrapper\"><div class=\"icon-embed-xxsmall w-embed\"><svg xmlns=\"http://www.w3.org/2000/svg\" width=\"100%\" height=\"100%\" viewBox=\"0 -960 960 960\"><path fill=\"currentColor\" d=\"M676.2-445.93H188.09q-14.68 0-24.37-9.7-9.7-9.7-9.7-24.37 0-14.67 9.7-24.37 9.69-9.7 24.37-9.7H676.2L456.13-734.13q-10.2-10.2-10.33-24.03-.14-13.84 10.07-24.09 10.22-10.29 24.09-10.17 13.87.12 24.15 10.31l278 278q5.46 5.52 7.94 11.48 2.49 5.97 2.49 12.66t-2.49 12.63q-2.48 5.95-7.94 11.45l-278.24 278q-10.55 10.43-24.17 10.43-13.61 0-23.81-10.49-10.19-10.21-10.19-23.85 0-13.63 10.19-23.83l220.31-220.3Z\"></path></svg></div></div></a></div><div role=\"listitem\" class=\"crosslink_item w-dyn-item\"><a list-link=\"trigger\" href=\"/immigration\" class=\"button is-text-link w-inline-block\"><div class=\"crosslink_item-text-wrapper\"><p>Immigration </p></div><div list-link=\"target\" class=\"crosslink_item-icon-wrapper\"><div class=\"icon-embed-xxsmall w-embed\"><svg xmlns=\"http://www.w3.org/2000/svg\" width=\"100%\" height=\"100%\" viewBox=\"0 -960 960 960\"><path fill=\"currentColor\" d=\"M676.2-445.93H188.09q-14.68 0-24.37-9.7-9.7-9.7-9.7-24.37 0-14.67 9.7-24.37 9.69-9.7 24.37-9.7H676.2L456.13-734.13q-10.2-10.2-10.33-24.03-.14-13.84 10.07-24.09 10.22-10.29 24.09-10.17 13.87.12 24.15 10.31l278 278q5.46 5.52 7.94 11.48 2.49 5.97 2.49 12.66t-2.49 12.63q-2.48 5.95-7.94 11.45l-278.24 278q-10.55 10.43-24.17 10.43-13.61 0-23.81-10.49-10.19-10.21-10.19-23.85 0-13.63 10.19-23.83l220.31-220.3Z\"></path></svg></div></div></a></div><div role=\"listitem\" class=\"crosslink_item w-dyn-item\"><a list-link=\"trigger\" href=\"/grievances\" class=\"button is-text-link w-inline-block\"><div class=\"crosslink_item-text-wrapper\"><p>Grievances </p></div><div list-link=\"target\" class=\"crosslink_item-icon-wrapper\"><div class=\"icon-embed-xxsmall w-embed\"><svg xmlns=\"http://www.w3.org/2000/svg\" width=\"100%\" height=\"100%\" viewBox=\"0 -960 960 960\"><path fill=\"currentColor\" d=\"M676.2-445.93H188.09q-14.68 0-24.37-9.7-9.7-9.7-9.7-24.37 0-14.67 9.7-24.37 9.69-9.7 24.37-9.7H676.2L456.13-734.13q-10.2-10.2-10.33-24.03-.14-13.84 10.07-24.09 10.22-10.29 24.09-10.17 13.87.12 24.15 10.31l278 278q5.46 5.52 7.94 11.48 2.49 5.97 2.49 12.66t-2.49 12.63q-2.48 5.95-7.94 11.45l-278.24 278q-10.55 10.43-24.17 10.43-13.61 0-23.81-10.49-10.19-10.21-10.19-23.85 0-13.63 10.19-23.83l220.31-220.3Z\"></path></svg></div></div></a></div><div role=\"listitem\" class=\"crosslink_item w-dyn-item\"><a list-link=\"trigger\" href=\"/gig-economy\" class=\"button is-text-link w-inline-block\"><div class=\"crosslink_item-text-wrapper\"><p>Gig Economy </p></div><div list-link=\"target\" class=\"crosslink_item-icon-wrapper\"><div class=\"icon-embed-xxsmall w-embed\"><svg xmlns=\"http://www.w3.org/2000/svg\" width=\"100%\" height=\"100%\" viewBox=\"0 -960 960 960\"><path fill=\"currentColor\" d=\"M676.2-445.93H188.09q-14.68 0-24.37-9.7-9.7-9.7-9.7-24.37 0-14.67 9.7-24.37 9.69-9.7 24.37-9.7H676.2L456.13-734.13q-10.2-10.2-10.33-24.03-.14-13.84 10.07-24.09 10.22-10.29 24.09-10.17 13.87.12 24.15 10.31l278 278q5.46 5.52 7.94 11.48 2.49 5.97 2.49 12.66t-2.49 12.63q-2.48 5.95-7.94 11.45l-278.24 278q-10.55 10.43-24.17 10.43-13.61 0-23.81-10.49-10.19-10.21-10.19-23.85 0-13.63 10.19-23.83l220.31-220.3Z\"></path></svg></div></div></a></div><div role=\"listitem\" class=\"crosslink_item w-dyn-item\"><a list-link=\"trigger\" href=\"/flexible-working\" class=\"button is-text-link w-inline-block\"><div class=\"crosslink_item-text-wrapper\"><p>Flexible Working</p></div><div list-link=\"target\" class=\"crosslink_item-icon-wrapper\"><div class=\"icon-embed-xxsmall w-embed\"><svg xmlns=\"http://www.w3.org/2000/svg\" width=\"100%\" height=\"100%\" viewBox=\"0 -960 960 960\"><path fill=\"currentColor\" d=\"M676.2-445.93H188.09q-14.68 0-24.37-9.7-9.7-9.7-9.7-24.37 0-14.67 9.7-24.37 9.69-9.7 24.37-9.7H676.2L456.13-734.13q-10.2-10.2-10.33-24.03-.14-13.84 10.07-24.09 10.22-10.29 24.09-10.17 13.87.12 24.15 10.31l278 278q5.46 5.52 7.94 11.48 2.49 5.97 2.49 12.66t-2.49 12.63q-2.48 5.95-7.94 11.45l-278.24 278q-10.55 10.43-24.17 10.43-13.61 0-23.81-10.49-10.19-10.21-10.19-23.85 0-13.63 10.19-23.83l220.31-220.3Z\"></path></svg></div></div></a></div><div role=\"listitem\" class=\"crosslink_item w-dyn-item\"><a list-link=\"trigger\" href=\"/discrimination\" class=\"button is-text-link w-inline-block\"><div class=\"crosslink_item-text-wrapper\"><p>Discrimination</p></div><div list-link=\"target\" class=\"crosslink_item-icon-wrapper\"><div class=\"icon-embed-xxsmall w-embed\"><svg xmlns=\"http://www.w3.org/2000/svg\" width=\"100%\" height=\"100%\" viewBox=\"0 -960 960 960\"><path fill=\"currentColor\" d=\"M676.2-445.93H188.09q-14.68 0-24.37-9.7-9.7-9.7-9.7-24.37 0-14.67 9.7-24.37 9.69-9.7 24.37-9.7H676.2L456.13-734.13q-10.2-10.2-10.33-24.03-.14-13.84 10.07-24.09 10.22-10.29 24.09-10.17 13.87.12 24.15 10.31l278 278q5.46 5.52 7.94 11.48 2.49 5.97 2.49 12.66t-2.49 12.63q-2.48 5.95-7.94 11.45l-278.24 278q-10.55 10.43-24.17 10.43-13.61 0-23.81-10.49-10.19-10.21-10.19-23.85 0-13.63 10.19-23.83l220.31-220.3Z\"></path></svg></div></div></a></div><div role=\"listitem\" class=\"crosslink_item w-dyn-item\"><a list-link=\"trigger\" href=\"/disciplinary-proceedings\" class=\"button is-text-link w-inline-block\"><div class=\"crosslink_item-text-wrapper\"><p>Disciplinary Proceedings</p></div><div list-link=\"target\" class=\"crosslink_item-icon-wrapper\"><div class=\"icon-embed-xxsmall w-embed\"><svg xmlns=\"http://www.w3.org/2000/svg\" width=\"100%\" height=\"100%\" viewBox=\"0 -960 960 960\"><path fill=\"currentColor\" d=\"M676.2-445.93H188.09q-14.68 0-24.37-9.7-9.7-9.7-9.7-24.37 0-14.67 9.7-24.37 9.69-9.7 24.37-9.7H676.2L456.13-734.13q-10.2-10.2-10.33-24.03-.14-13.84 10.07-24.09 10.22-10.29 24.09-10.17 13.87.12 24.15 10.31l278 278q5.46 5.52 7.94 11.48 2.49 5.97 2.49 12.66t-2.49 12.63q-2.48 5.95-7.94 11.45l-278.24 278q-10.55 10.43-24.17 10.43-13.61 0-23.81-10.49-10.19-10.21-10.19-23.85 0-13.63 10.19-23.83l220.31-220.3Z\"></path></svg></div></div></a></div><div role=\"listitem\" class=\"crosslink_item w-dyn-item\"><a list-link=\"trigger\" href=\"/directors-service-agreements\" class=\"button is-text-link w-inline-block\"><div class=\"crosslink_item-text-wrapper\"><p>Directors&#x27; Service Agreements </p></div><div list-link=\"target\" class=\"crosslink_item-icon-wrapper\"><div class=\"icon-embed-xxsmall w-embed\"><svg xmlns=\"http://www.w3.org/2000/svg\" width=\"100%\" height=\"100%\" viewBox=\"0 -960 960 960\"><path fill=\"currentColor\" d=\"M676.2-445.93H188.09q-14.68 0-24.37-9.7-9.7-9.7-9.7-24.37 0-14.67 9.7-24.37 9.69-9.7 24.37-9.7H676.2L456.13-734.13q-10.2-10.2-10.33-24.03-.14-13.84 10.07-24.09 10.22-10.29 24.09-10.17 13.87.12 24.15 10.31l278 278q5.46 5.52 7.94 11.48 2.49 5.97 2.49 12.66t-2.49 12.63q-2.48 5.95-7.94 11.45l-278.24 278q-10.55 10.43-24.17 10.43-13.61 0-23.81-10.49-10.19-10.21-10.19-23.85 0-13.63 10.19-23.83l220.31-220.3Z\"></path></svg></div></div></a></div><div role=\"listitem\" class=\"crosslink_item w-dyn-item\"><a list-link=\"trigger\" href=\"/contracts-of-employment\" class=\"button is-text-link w-inline-block\"><div class=\"crosslink_item-text-wrapper\"><p>Contracts of Employment </p></div><div list-link=\"target\" class=\"crosslink_item-icon-wrapper\"><div class=\"icon-embed-xxsmall w-embed\"><svg xmlns=\"http://www.w3.org/2000/svg\" width=\"100%\" height=\"100%\" viewBox=\"0 -960 960 960\"><path fill=\"currentColor\" d=\"M676.2-445.93H188.09q-14.68 0-24.37-9.7-9.7-9.7-9.7-24.37 0-14.67 9.7-24.37 9.69-9.7 24.37-9.7H676.2L456.13-734.13q-10.2-10.2-10.33-24.03-.14-13.84 10.07-24.09 10.22-10.29 24.09-10.17 13.87.12 24.15 10.31l278 278q5.46 5.52 7.94 11.48 2.49 5.97 2.49 12.66t-2.49 12.63q-2.48 5.95-7.94 11.45l-278.24 278q-10.55 10.43-24.17 10.43-13.61 0-23.81-10.49-10.19-10.21-10.19-23.85 0-13.63 10.19-23.83l220.31-220.3Z\"></path></svg></div></div></a></div><div role=\"listitem\" class=\"crosslink_item w-dyn-item\"><a list-link=\"trigger\" href=\"/commercial-agents\" class=\"button is-text-link w-inline-block\"><div class=\"crosslink_item-text-wrapper\"><p>Commercial Agents</p></div><div list-link=\"target\" class=\"crosslink_item-icon-wrapper\"><div class=\"icon-embed-xxsmall w-embed\"><svg xmlns=\"http://www.w3.org/2000/svg\" width=\"100%\" height=\"100%\" viewBox=\"0 -960 960 960\"><path fill=\"currentColor\" d=\"M676.2-445.93H188.09q-14.68 0-24.37-9.7-9.7-9.7-9.7-24.37 0-14.67 9.7-24.37 9.69-9.7 24.37-9.7H676.2L456.13-734.13q-10.2-10.2-10.33-24.03-.14-13.84 10.07-24.09 10.22-10.29 24.09-10.17 13.87.12 24.15 10.31l278 278q5.46 5.52 7.94 11.48 2.49 5.97 2.49 12.66t-2.49 12.63q-2.48 5.95-7.94 11.45l-278.24 278q-10.55 10.43-24.17 10.43-13.61 0-23.81-10.49-10.19-10.21-10.19-23.85 0-13.63 10.19-23.83l220.31-220.3Z\"></path></svg></div></div></a></div><div role=\"listitem\" class=\"crosslink_item w-dyn-item\"><a list-link=\"trigger\" href=\"/breach-of-contract-and-unlawful-deduction-from-wages-for-employers\" class=\"button is-text-link w-inline-block\"><div class=\"crosslink_item-text-wrapper\"><p>Breach of Contract and Unlawful Deduction from Wages for Employers</p></div><div list-link=\"target\" class=\"crosslink_item-icon-wrapper\"><div class=\"icon-embed-xxsmall w-embed\"><svg xmlns=\"http://www.w3.org/2000/svg\" width=\"100%\" height=\"100%\" viewBox=\"0 -960 960 960\"><path fill=\"currentColor\" d=\"M676.2-445.93H188.09q-14.68 0-24.37-9.7-9.7-9.7-9.7-24.37 0-14.67 9.7-24.37 9.69-9.7 24.37-9.7H676.2L456.13-734.13q-10.2-10.2-10.33-24.03-.14-13.84 10.07-24.09 10.22-10.29 24.09-10.17 13.87.12 24.15 10.31l278 278q5.46 5.52 7.94 11.48 2.49 5.97 2.49 12.66t-2.49 12.63q-2.48 5.95-7.94 11.45l-278.24 278q-10.55 10.43-24.17 10.43-13.61 0-23.81-10.49-10.19-10.21-10.19-23.85 0-13.63 10.19-23.83l220.31-220.3Z\"></path></svg></div></div></a></div></div></div></div></div></div></div></div></section>"}]}
